django_instapush-1.0.4.dist-info/DESCRIPTION.rst
django_instapush-1.0.4.dist-info/METADATA
django_instapush-1.0.4.dist-info/RECORD
django_instapush-1.0.4.dist-info/WHEEL
django_instapush-1.0.4.dist-info/metadata.json
django_instapush-1.0.4.dist-info/pbr.json
django_instapush-1.0.4.dist-info/top_level.txt
instapush/__init__.py
instapush/exceptions.py
instapush/settings.py
instapush/utils.py
instapush/libs/__init__.py
instapush/libs/apns.py
instapush/libs/gcm.py
instapush/models/__init__.py
instapush/models/base.py
instapush/models/fields.py
instapush/models/managers.py
instapush/models/mongo.py
instapush/models/querysets.py
