Metadata-Version: 2.0
Name: django-instapush
Version: 1.0.4
Summary: Send push notifications to android and ios devices
Home-page: https://github.com/amyth/django-instapush
Author: Amyth Arora
Author-email: mail@amythsingh.com
License: MIT License
Platform: UNKNOWN
Requires-Dist: requests (>=2.8.1)
Requires-Dist: requests-toolbelt (>=0.4.0)
